[{"nodeName":"method-1-ComposedSplitFunction(PromotionFunction<DATA>,PartitionFunction<DATA>)","category":"openclover-method","ifCatch":true},{"nodeName":"statement-1-ComposedSplitFunction(PromotionFunction<DATA>,PartitionFunction<DATA>)","category":"openclover-statement","ifCatch":true},{"nodeName":"statement-2-ComposedSplitFunction(PromotionFunction<DATA>,PartitionFunction<DATA>)","category":"openclover-statement","ifCatch":true},{"nodeName":"method-2-process(Set<DATA>,DistanceFunction<? super DATA>) : SplitResult<DATA>","category":"openclover-method","ifCatch":true},{"nodeName":"statement-3-process(Set<DATA>,DistanceFunction<? super DATA>) : SplitResult<DATA>","category":"openclover-statement","ifCatch":true},{"nodeName":"statement-4-process(Set<DATA>,DistanceFunction<? super DATA>) : SplitResult<DATA>","category":"openclover-statement","ifCatch":true},{"nodeName":"statement-5-process(Set<DATA>,DistanceFunction<? super DATA>) : SplitResult<DATA>","category":"openclover-statement","ifCatch":true},{"nodeName":"method-3-DistanceFunctions()","category":"openclover-method","ifCatch":false},{"nodeName":"method-4-cached(DistanceFunction<Data>) : DistanceFunction<Data>","category":"openclover-method","ifCatch":true},{"nodeName":"statement-6-cached(DistanceFunction<Data>) : DistanceFunction<Data>","category":"openclover-statement","ifCatch":true},{"nodeName":"method-5-Pair(Data,Data)","category":"openclover-method","ifCatch":true},{"nodeName":"statement-7-Pair(Data,Data)","category":"openclover-statement","ifCatch":true},{"nodeName":"statement-8-Pair(Data,Data)","category":"openclover-statement","ifCatch":true},{"nodeName":"method-6-hashCode() : int","category":"openclover-method","ifCatch":true},{"nodeName":"statement-9-hashCode() : int","category":"openclover-statement","ifCatch":true},{"nodeName":"method-7-equals(Object) : boolean","category":"openclover-method","ifCatch":true},{"nodeName":"statement-10-equals(Object) : boolean","category":"openclover-statement","ifCatch":true},{"nodeName":"branch-1-equals(Object) : boolean","category":"openclover-branch","ifCatch":true},{"nodeName":"branch-2-equals(Object) : boolean","category":"openclover-branch","ifCatch":false},{"nodeName":"statement-11-equals(Object) : boolean","category":"openclover-statement","ifCatch":true},{"nodeName":"statement-12-equals(Object) : boolean","category":"openclover-statement","ifCatch":true},{"nodeName":"statement-13-equals(Object) : boolean","category":"openclover-statement","ifCatch":false},{"nodeName":"method-8-calculate(Data,Data) : double","category":"openclover-method","ifCatch":true},{"nodeName":"statement-14-calculate(Data,Data) : double","category":"openclover-statement","ifCatch":true},{"nodeName":"statement-15-calculate(Data,Data) : double","category":"openclover-statement","ifCatch":true},{"nodeName":"statement-16-calculate(Data,Data) : double","category":"openclover-statement","ifCatch":true},{"nodeName":"branch-3-calculate(Data,Data) : double","category":"openclover-branch","ifCatch":true},{"nodeName":"branch-4-calculate(Data,Data) : double","category":"openclover-branch","ifCatch":true},{"nodeName":"statement-17-calculate(Data,Data) : double","category":"openclover-statement","ifCatch":true},{"nodeName":"statement-18-calculate(Data,Data) : double","category":"openclover-statement","ifCatch":true},{"nodeName":"statement-19-calculate(Data,Data) : double","category":"openclover-statement","ifCatch":true},{"nodeName":"statement-20-calculate(Data,Data) : double","category":"openclover-statement","ifCatch":true},{"nodeName":"branch-5-calculate(Data,Data) : double","category":"openclover-branch","ifCatch":false},{"nodeName":"branch-6-calculate(Data,Data) : double","category":"openclover-branch","ifCatch":true},{"nodeName":"statement-21-calculate(Data,Data) : double","category":"openclover-statement","ifCatch":false},{"nodeName":"statement-22-calculate(Data,Data) : double","category":"openclover-statement","ifCatch":true},{"nodeName":"statement-23-calculate(Data,Data) : double","category":"openclover-statement","ifCatch":true},{"nodeName":"statement-24-calculate(Data,Data) : double","category":"openclover-statement","ifCatch":true},{"nodeName":"statement-25-calculate(Data,Data) : double","category":"openclover-statement","ifCatch":true},{"nodeName":"method-9-euclidean(EuclideanCoordinate,EuclideanCoordinate) : double","category":"openclover-method","ifCatch":true},{"nodeName":"statement-26-euclidean(EuclideanCoordinate,EuclideanCoordinate) : double","category":"openclover-statement","ifCatch":true},{"nodeName":"statement-27-euclidean(EuclideanCoordinate,EuclideanCoordinate) : double","category":"openclover-statement","ifCatch":true},{"nodeName":"statement-28-euclidean(EuclideanCoordinate,EuclideanCoordinate) : double","category":"openclover-statement","ifCatch":true},{"nodeName":"branch-7-euclidean(EuclideanCoordinate,EuclideanCoordinate) : double","category":"openclover-branch","ifCatch":true},{"nodeName":"branch-8-euclidean(EuclideanCoordinate,EuclideanCoordinate) : double","category":"openclover-branch","ifCatch":true},{"nodeName":"statement-29-euclidean(EuclideanCoordinate,EuclideanCoordinate) : double","category":"openclover-statement","ifCatch":true},{"nodeName":"statement-30-euclidean(EuclideanCoordinate,EuclideanCoordinate) : double","category":"openclover-statement","ifCatch":true},{"nodeName":"statement-31-euclidean(EuclideanCoordinate,EuclideanCoordinate) : double","category":"openclover-statement","ifCatch":true},{"nodeName":"statement-32-euclidean(EuclideanCoordinate,EuclideanCoordinate) : double","category":"openclover-statement","ifCatch":true},{"nodeName":"method-10-calculate(EuclideanCoordinate,EuclideanCoordinate) : double","category":"openclover-method","ifCatch":false},{"nodeName":"statement-33-calculate(EuclideanCoordinate,EuclideanCoordinate) : double","category":"openclover-statement","ifCatch":false},{"nodeName":"method-11-calculate(List<Integer>,List<Integer>) : double","category":"openclover-method","ifCatch":true},{"nodeName":"method-12-IntegerListEuclideanCoordinate(List<Integer>)","category":"openclover-method","ifCatch":true},{"nodeName":"statement-34-IntegerListEuclideanCoordinate(List<Integer>)","category":"openclover-statement","ifCatch":true},{"nodeName":"method-13-dimensions() : int","category":"openclover-method","ifCatch":true},{"nodeName":"statement-35-dimensions() : int","category":"openclover-statement","ifCatch":true},{"nodeName":"method-14-get(int) : double","category":"openclover-method","ifCatch":true},{"nodeName":"statement-36-get(int) : double","category":"openclover-statement","ifCatch":true},{"nodeName":"statement-37-get(int) : double","category":"openclover-statement","ifCatch":true},{"nodeName":"statement-38-get(int) : double","category":"openclover-statement","ifCatch":true},{"nodeName":"statement-39-get(int) : double","category":"openclover-statement","ifCatch":true},{"nodeName":"statement-40-get(int) : double","category":"openclover-statement","ifCatch":true},{"nodeName":"method-15-calculate(List<Double>,List<Double>) : double","category":"openclover-method","ifCatch":true},{"nodeName":"method-16-DoubleListEuclideanCoordinate(List<Double>)","category":"openclover-method","ifCatch":true},{"nodeName":"statement-41-DoubleListEuclideanCoordinate(List<Double>)","category":"openclover-statement","ifCatch":true},{"nodeName":"method-17-dimensions() : int","category":"openclover-method","ifCatch":true},{"nodeName":"statement-42-dimensions() : int","category":"openclover-statement","ifCatch":true},{"nodeName":"method-18-get(int) : double","category":"openclover-method","ifCatch":true},{"nodeName":"statement-43-get(int) : double","category":"openclover-statement","ifCatch":true},{"nodeName":"statement-44-get(int) : double","category":"openclover-statement","ifCatch":true},{"nodeName":"statement-45-get(int) : double","category":"openclover-statement","ifCatch":true},{"nodeName":"statement-46-get(int) : double","category":"openclover-statement","ifCatch":true},{"nodeName":"statement-47-get(int) : double","category":"openclover-statement","ifCatch":true},{"nodeName":"method-19-ResultItem(DATA,double)","category":"openclover-method","ifCatch":true},{"nodeName":"statement-48-ResultItem(DATA,double)","category":"openclover-statement","ifCatch":true},{"nodeName":"statement-49-ResultItem(DATA,double)","category":"openclover-statement","ifCatch":true},{"nodeName":"method-20-SplitNodeReplacement(Object)","category":"openclover-method","ifCatch":true},{"nodeName":"statement-50-SplitNodeReplacement(Object)","category":"openclover-statement","ifCatch":true},{"nodeName":"method-21-RootNodeReplacement(Object)","category":"openclover-method","ifCatch":true},{"nodeName":"statement-51-RootNodeReplacement(Object)","category":"openclover-statement","ifCatch":true},{"nodeName":"method-22-ItemWithDistances(U,double,double)","category":"openclover-method","ifCatch":true},{"nodeName":"statement-52-ItemWithDistances(U,double,double)","category":"openclover-statement","ifCatch":true},{"nodeName":"statement-53-ItemWithDistances(U,double,double)","category":"openclover-statement","ifCatch":true},{"nodeName":"statement-54-ItemWithDistances(U,double,double)","category":"openclover-statement","ifCatch":true},{"nodeName":"method-23-compareTo(ItemWithDistances<U>) : int","category":"openclover-method","ifCatch":true},{"nodeName":"statement-55-compareTo(ItemWithDistances<U>) : int","category":"openclover-statement","ifCatch":true},{"nodeName":"branch-9-compareTo(ItemWithDistances<U>) : int","category":"openclover-branch","ifCatch":true},{"nodeName":"branch-10-compareTo(ItemWithDistances<U>) : int","category":"openclover-branch","ifCatch":true},{"nodeName":"statement-56-compareTo(ItemWithDistances<U>) : int","category":"openclover-statement","ifCatch":true},{"nodeName":"statement-57-compareTo(ItemWithDistances<U>) : int","category":"openclover-statement","ifCatch":true},{"nodeName":"branch-11-compareTo(ItemWithDistances<U>) : int","category":"openclover-branch","ifCatch":true},{"nodeName":"branch-12-compareTo(ItemWithDistances<U>) : int","category":"openclover-branch","ifCatch":true},{"nodeName":"statement-58-compareTo(ItemWithDistances<U>) : int","category":"openclover-statement","ifCatch":true},{"nodeName":"statement-59-compareTo(ItemWithDistances<U>) : int","category":"openclover-statement","ifCatch":true},{"nodeName":"method-24-ResultsIterator()","category":"openclover-method","ifCatch":true},{"nodeName":"statement-60-ResultsIterator()","category":"openclover-statement","ifCatch":true},{"nodeName":"branch-13-ResultsIterator()","category":"openclover-branch","ifCatch":true},{"nodeName":"branch-14-ResultsIterator()","category":"openclover-branch","ifCatch":true},{"nodeName":"statement-61-ResultsIterator()","category":"openclover-statement","ifCatch":true},{"nodeName":"statement-62-ResultsIterator()","category":"openclover-statement","ifCatch":true},{"nodeName":"statement-63-ResultsIterator()","category":"openclover-statement","ifCatch":true},{"nodeName":"statement-64-ResultsIterator()","category":"openclover-statement","ifCatch":true},{"nodeName":"statement-65-ResultsIterator()","category":"openclover-statement","ifCatch":true},{"nodeName":"statement-66-ResultsIterator()","category":"openclover-statement","ifCatch":true},{"nodeName":"method-25-hasNext() : boolean","category":"openclover-method","ifCatch":true},{"nodeName":"statement-67-hasNext() : boolean","category":"openclover-statement","ifCatch":true},{"nodeName":"branch-15-hasNext() : boolean","category":"openclover-branch","ifCatch":true},{"nodeName":"branch-16-hasNext() : boolean","category":"openclover-branch","ifCatch":true},{"nodeName":"statement-68-hasNext() : boolean","category":"openclover-statement","ifCatch":true},{"nodeName":"statement-69-hasNext() : boolean","category":"openclover-statement","ifCatch":true},{"nodeName":"branch-17-hasNext() : boolean","category":"openclover-branch","ifCatch":true},{"nodeName":"branch-18-hasNext() : boolean","category":"openclover-branch","ifCatch":false},{"nodeName":"statement-70-hasNext() : boolean","category":"openclover-statement","ifCatch":true},{"nodeName":"statement-71-hasNext() : boolean","category":"openclover-statement","ifCatch":true},{"nodeName":"branch-19-hasNext() : boolean","category":"openclover-branch","ifCatch":true},{"nodeName":"branch-20-hasNext() : boolean","category":"openclover-branch","ifCatch":true},{"nodeName":"statement-72-hasNext() : boolean","category":"openclover-statement","ifCatch":true},{"nodeName":"statement-73-hasNext() : boolean","category":"openclover-statement","ifCatch":true},{"nodeName":"statement-74-hasNext() : boolean","category":"openclover-statement","ifCatch":true},{"nodeName":"method-26-next() : ResultItem","category":"openclover-method","ifCatch":true},{"nodeName":"statement-75-next() : ResultItem","category":"openclover-statement","ifCatch":true},{"nodeName":"branch-21-next() : ResultItem","category":"openclover-branch","ifCatch":true},{"nodeName":"branch-22-next() : ResultItem","category":"openclover-branch","ifCatch":true},{"nodeName":"statement-76-next() : ResultItem","category":"openclover-statement","ifCatch":true},{"nodeName":"statement-77-next() : ResultItem","category":"openclover-statement","ifCatch":true},{"nodeName":"statement-78-next() : ResultItem","category":"openclover-statement","ifCatch":true},{"nodeName":"statement-79-next() : ResultItem","category":"openclover-statement","ifCatch":true},{"nodeName":"method-27-remove() : void","category":"openclover-method","ifCatch":false},{"nodeName":"statement-80-remove() : void","category":"openclover-statement","ifCatch":false},{"nodeName":"method-28-fetchNext() : void","category":"openclover-method","ifCatch":true},{"nodeName":"branch-23-fetchNext() : void","category":"openclover-branch","ifCatch":true},{"nodeName":"branch-24-fetchNext() : void","category":"openclover-branch","ifCatch":false},{"nodeName":"statement-81-fetchNext() : void","category":"openclover-statement","ifCatch":true},{"nodeName":"branch-25-fetchNext() : void","category":"openclover-branch","ifCatch":true},{"nodeName":"branch-26-fetchNext() : void","category":"openclover-branch","ifCatch":true},{"nodeName":"statement-82-fetchNext() : void","category":"openclover-statement","ifCatch":true},{"nodeName":"statement-83-fetchNext() : void","category":"openclover-statement","ifCatch":true},{"nodeName":"statement-84-fetchNext() : void","category":"openclover-statement","ifCatch":true},{"nodeName":"branch-27-fetchNext() : void","category":"openclover-branch","ifCatch":true},{"nodeName":"branch-28-fetchNext() : void","category":"openclover-branch","ifCatch":true},{"nodeName":"statement-85-fetchNext() : void","category":"openclover-statement","ifCatch":true},{"nodeName":"branch-29-fetchNext() : void","category":"openclover-branch","ifCatch":true},{"nodeName":"branch-30-fetchNext() : void","category":"openclover-branch","ifCatch":true},{"nodeName":"statement-86-fetchNext() : void","category":"openclover-statement","ifCatch":true},{"nodeName":"branch-31-fetchNext() : void","category":"openclover-branch","ifCatch":true},{"nodeName":"branch-32-fetchNext() : void","category":"openclover-branch","ifCatch":false},{"nodeName":"statement-87-fetchNext() : void","category":"openclover-statement","ifCatch":true},{"nodeName":"statement-88-fetchNext() : void","category":"openclover-statement","ifCatch":true},{"nodeName":"statement-89-fetchNext() : void","category":"openclover-statement","ifCatch":true},{"nodeName":"statement-90-fetchNext() : void","category":"openclover-statement","ifCatch":true},{"nodeName":"branch-33-fetchNext() : void","category":"openclover-branch","ifCatch":true},{"nodeName":"branch-34-fetchNext() : void","category":"openclover-branch","ifCatch":true},{"nodeName":"statement-91-fetchNext() : void","category":"openclover-statement","ifCatch":true},{"nodeName":"statement-92-fetchNext() : void","category":"openclover-statement","ifCatch":true},{"nodeName":"statement-93-fetchNext() : void","category":"openclover-statement","ifCatch":true},{"nodeName":"branch-35-fetchNext() : void","category":"openclover-branch","ifCatch":true},{"nodeName":"branch-36-fetchNext() : void","category":"openclover-branch","ifCatch":false},{"nodeName":"statement-94-fetchNext() : void","category":"openclover-statement","ifCatch":true},{"nodeName":"branch-37-fetchNext() : void","category":"openclover-branch","ifCatch":true},{"nodeName":"branch-38-fetchNext() : void","category":"openclover-branch","ifCatch":true},{"nodeName":"statement-95-fetchNext() : void","category":"openclover-statement","ifCatch":true},{"nodeName":"statement-96-fetchNext() : void","category":"openclover-statement","ifCatch":true},{"nodeName":"statement-97-fetchNext() : void","category":"openclover-statement","ifCatch":true},{"nodeName":"statement-98-fetchNext() : void","category":"openclover-statement","ifCatch":true},{"nodeName":"statement-99-fetchNext() : void","category":"openclover-statement","ifCatch":true},{"nodeName":"branch-39-fetchNext() : void","category":"openclover-branch","ifCatch":true},{"nodeName":"branch-40-fetchNext() : void","category":"openclover-branch","ifCatch":true},{"nodeName":"statement-100-fetchNext() : void","category":"openclover-statement","ifCatch":true},{"nodeName":"statement-101-fetchNext() : void","category":"openclover-statement","ifCatch":true},{"nodeName":"statement-102-fetchNext() : void","category":"openclover-statement","ifCatch":true},{"nodeName":"method-29-prepareNextNearest() : boolean","category":"openclover-method","ifCatch":true},{"nodeName":"statement-103-prepareNextNearest() : boolean","category":"openclover-statement","ifCatch":true},{"nodeName":"branch-41-prepareNextNearest() : boolean","category":"openclover-branch","ifCatch":true},{"nodeName":"branch-42-prepareNextNearest() : boolean","category":"openclover-branch","ifCatch":true},{"nodeName":"statement-104-prepareNextNearest() : boolean","category":"openclover-statement","ifCatch":true},{"nodeName":"statement-105-prepareNextNearest() : boolean","category":"openclover-statement","ifCatch":true},{"nodeName":"branch-43-prepareNextNearest() : boolean","category":"openclover-branch","ifCatch":true},{"nodeName":"branch-44-prepareNextNearest() : boolean","category":"openclover-branch","ifCatch":true},{"nodeName":"statement-106-prepareNextNearest() : boolean","category":"openclover-statement","ifCatch":true},{"nodeName":"statement-107-prepareNextNearest() : boolean","category":"openclover-statement","ifCatch":true},{"nodeName":"statement-108-prepareNextNearest() : boolean","category":"openclover-statement","ifCatch":true},{"nodeName":"statement-109-prepareNextNearest() : boolean","category":"openclover-statement","ifCatch":true},{"nodeName":"statement-110-prepareNextNearest() : boolean","category":"openclover-statement","ifCatch":true},{"nodeName":"method-30-Query(DATA,double,int)","category":"openclover-method","ifCatch":true},{"nodeName":"statement-111-Query(DATA,double,int)","category":"openclover-statement","ifCatch":true},{"nodeName":"statement-112-Query(DATA,double,int)","category":"openclover-statement","ifCatch":true},{"nodeName":"statement-113-Query(DATA,double,int)","category":"openclover-statement","ifCatch":true},{"nodeName":"method-31-iterator() : Iterator<ResultItem>","category":"openclover-method","ifCatch":true},{"nodeName":"statement-114-iterator() : Iterator<ResultItem>","category":"openclover-statement","ifCatch":true},{"nodeName":"method-32-MTree(DistanceFunction<? super DATA>,SplitFunction<DATA>)","category":"openclover-method","ifCatch":true},{"nodeName":"statement-115-MTree(DistanceFunction<? super DATA>,SplitFunction<DATA>)","category":"openclover-statement","ifCatch":true},{"nodeName":"method-33-MTree(int,DistanceFunction<? super DATA>,SplitFunction<DATA>)","category":"openclover-method","ifCatch":true},{"nodeName":"statement-116-MTree(int,DistanceFunction<? super DATA>,SplitFunction<DATA>)","category":"openclover-statement","ifCatch":true},{"nodeName":"method-34-MTree(int,int,DistanceFunction<? super DATA>,SplitFunction<DATA>)","category":"openclover-method","ifCatch":true},{"nodeName":"statement-117-MTree(int,int,DistanceFunction<? super DATA>,SplitFunction<DATA>)","category":"openclover-statement","ifCatch":true},{"nodeName":"branch-45-MTree(int,int,DistanceFunction<? super DATA>,SplitFunction<DATA>)","category":"openclover-branch","ifCatch":true},{"nodeName":"branch-46-MTree(int,int,DistanceFunction<? super DATA>,SplitFunction<DATA>)","category":"openclover-branch","ifCatch":true},{"nodeName":"statement-118-MTree(int,int,DistanceFunction<? super DATA>,SplitFunction<DATA>)","category":"openclover-statement","ifCatch":true},{"nodeName":"statement-119-MTree(int,int,DistanceFunction<? super DATA>,SplitFunction<DATA>)","category":"openclover-statement","ifCatch":true},{"nodeName":"branch-47-MTree(int,int,DistanceFunction<? super DATA>,SplitFunction<DATA>)","category":"openclover-branch","ifCatch":true},{"nodeName":"branch-48-MTree(int,int,DistanceFunction<? super DATA>,SplitFunction<DATA>)","category":"openclover-branch","ifCatch":true},{"nodeName":"statement-120-MTree(int,int,DistanceFunction<? super DATA>,SplitFunction<DATA>)","category":"openclover-statement","ifCatch":true},{"nodeName":"statement-121-MTree(int,int,DistanceFunction<? super DATA>,SplitFunction<DATA>)","category":"openclover-statement","ifCatch":true},{"nodeName":"statement-122-MTree(int,int,DistanceFunction<? super DATA>,SplitFunction<DATA>)","category":"openclover-statement","ifCatch":true},{"nodeName":"statement-123-MTree(int,int,DistanceFunction<? super DATA>,SplitFunction<DATA>)","category":"openclover-statement","ifCatch":true},{"nodeName":"statement-124-MTree(int,int,DistanceFunction<? super DATA>,SplitFunction<DATA>)","category":"openclover-statement","ifCatch":true},{"nodeName":"statement-125-MTree(int,int,DistanceFunction<? super DATA>,SplitFunction<DATA>)","category":"openclover-statement","ifCatch":true},{"nodeName":"method-35-add(DATA) : void","category":"openclover-method","ifCatch":true},{"nodeName":"statement-126-add(DATA) : void","category":"openclover-statement","ifCatch":true},{"nodeName":"branch-49-add(DATA) : void","category":"openclover-branch","ifCatch":true},{"nodeName":"branch-50-add(DATA) : void","category":"openclover-branch","ifCatch":true},{"nodeName":"statement-127-add(DATA) : void","category":"openclover-statement","ifCatch":true},{"nodeName":"statement-128-add(DATA) : void","category":"openclover-statement","ifCatch":true},{"nodeName":"statement-129-add(DATA) : void","category":"openclover-statement","ifCatch":true},{"nodeName":"statement-130-add(DATA) : void","category":"openclover-statement","ifCatch":false},{"nodeName":"statement-131-add(DATA) : void","category":"openclover-statement","ifCatch":true},{"nodeName":"statement-132-add(DATA) : void","category":"openclover-statement","ifCatch":true},{"nodeName":"statement-133-add(DATA) : void","category":"openclover-statement","ifCatch":true},{"nodeName":"statement-134-add(DATA) : void","category":"openclover-statement","ifCatch":true},{"nodeName":"statement-135-add(DATA) : void","category":"openclover-statement","ifCatch":true},{"nodeName":"statement-136-add(DATA) : void","category":"openclover-statement","ifCatch":true},{"nodeName":"branch-51-add(DATA) : void","category":"openclover-branch","ifCatch":true},{"nodeName":"branch-52-add(DATA) : void","category":"openclover-branch","ifCatch":true},{"nodeName":"statement-137-add(DATA) : void","category":"openclover-statement","ifCatch":true},{"nodeName":"statement-138-add(DATA) : void","category":"openclover-statement","ifCatch":true},{"nodeName":"statement-139-add(DATA) : void","category":"openclover-statement","ifCatch":true},{"nodeName":"method-36-remove(DATA) : boolean","category":"openclover-method","ifCatch":true},{"nodeName":"statement-140-remove(DATA) : boolean","category":"openclover-statement","ifCatch":true},{"nodeName":"branch-53-remove(DATA) : boolean","category":"openclover-branch","ifCatch":true},{"nodeName":"branch-54-remove(DATA) : boolean","category":"openclover-branch","ifCatch":true},{"nodeName":"statement-141-remove(DATA) : boolean","category":"openclover-statement","ifCatch":true},{"nodeName":"statement-142-remove(DATA) : boolean","category":"openclover-statement","ifCatch":true},{"nodeName":"statement-143-remove(DATA) : boolean","category":"openclover-statement","ifCatch":true},{"nodeName":"statement-144-remove(DATA) : boolean","category":"openclover-statement","ifCatch":true},{"nodeName":"statement-145-remove(DATA) : boolean","category":"openclover-statement","ifCatch":true},{"nodeName":"statement-146-remove(DATA) : boolean","category":"openclover-statement","ifCatch":true},{"nodeName":"statement-147-remove(DATA) : boolean","category":"openclover-statement","ifCatch":true},{"nodeName":"statement-148-remove(DATA) : boolean","category":"openclover-statement","ifCatch":false},{"nodeName":"statement-149-remove(DATA) : boolean","category":"openclover-statement","ifCatch":true},{"nodeName":"method-37-getNearestByRange(DATA,double) : Query","category":"openclover-method","ifCatch":true},{"nodeName":"statement-150-getNearestByRange(DATA,double) : Query","category":"openclover-statement","ifCatch":true},{"nodeName":"method-38-getNearestByLimit(DATA,int) : Query","category":"openclover-method","ifCatch":true},{"nodeName":"statement-151-getNearestByLimit(DATA,int) : Query","category":"openclover-statement","ifCatch":true},{"nodeName":"method-39-getNearest(DATA,double,int) : Query","category":"openclover-method","ifCatch":true},{"nodeName":"statement-152-getNearest(DATA,double,int) : Query","category":"openclover-statement","ifCatch":true},{"nodeName":"method-40-getNearest(DATA) : Query","category":"openclover-method","ifCatch":true},{"nodeName":"statement-153-getNearest(DATA) : Query","category":"openclover-statement","ifCatch":true},{"nodeName":"method-41-_check() : void","category":"openclover-method","ifCatch":true},{"nodeName":"statement-154-_check() : void","category":"openclover-statement","ifCatch":true},{"nodeName":"branch-55-_check() : void","category":"openclover-branch","ifCatch":true},{"nodeName":"branch-56-_check() : void","category":"openclover-branch","ifCatch":true},{"nodeName":"statement-155-_check() : void","category":"openclover-statement","ifCatch":true},{"nodeName":"method-42-IndexItem(DATA)","category":"openclover-method","ifCatch":true},{"nodeName":"statement-156-IndexItem(DATA)","category":"openclover-statement","ifCatch":true},{"nodeName":"statement-157-IndexItem(DATA)","category":"openclover-statement","ifCatch":true},{"nodeName":"statement-158-IndexItem(DATA)","category":"openclover-statement","ifCatch":true},{"nodeName":"method-43-_check() : int","category":"openclover-method","ifCatch":true},{"nodeName":"statement-159-_check() : int","category":"openclover-statement","ifCatch":true},{"nodeName":"statement-160-_check() : int","category":"openclover-statement","ifCatch":true},{"nodeName":"statement-161-_check() : int","category":"openclover-statement","ifCatch":true},{"nodeName":"method-44-_checkRadius() : void","category":"openclover-method","ifCatch":true},{"nodeName":"branch-57-_checkRadius() : void","category":"openclover-branch","ifCatch":true},{"nodeName":"branch-58-_checkRadius() : void","category":"openclover-branch","ifCatch":false},{"nodeName":"method-45-_checkDistanceToParent() : void","category":"openclover-method","ifCatch":true},{"nodeName":"branch-59-_checkDistanceToParent() : void","category":"openclover-branch","ifCatch":true},{"nodeName":"branch-60-_checkDistanceToParent() : void","category":"openclover-branch","ifCatch":false},{"nodeName":"branch-61-_checkDistanceToParent() : void","category":"openclover-branch","ifCatch":true},{"nodeName":"branch-62-_checkDistanceToParent() : void","category":"openclover-branch","ifCatch":false},{"nodeName":"branch-63-_checkDistanceToParent() : void","category":"openclover-branch","ifCatch":true},{"nodeName":"branch-64-_checkDistanceToParent() : void","category":"openclover-branch","ifCatch":false},{"nodeName":"method-46-Node(DATA,R,L)","category":"openclover-method","ifCatch":true},{"nodeName":"statement-162-Node(DATA,R,L)","category":"openclover-statement","ifCatch":true},{"nodeName":"statement-163-Node(DATA,R,L)","category":"openclover-statement","ifCatch":true},{"nodeName":"statement-164-Node(DATA,R,L)","category":"openclover-statement","ifCatch":true},{"nodeName":"statement-165-Node(DATA,R,L)","category":"openclover-statement","ifCatch":true},{"nodeName":"statement-166-Node(DATA,R,L)","category":"openclover-statement","ifCatch":true},{"nodeName":"method-47-addData(DATA,double) : void","category":"openclover-method","ifCatch":true},{"nodeName":"statement-167-addData(DATA,double) : void","category":"openclover-statement","ifCatch":true},{"nodeName":"statement-168-addData(DATA,double) : void","category":"openclover-statement","ifCatch":true},{"nodeName":"method-48-_check() : int","category":"openclover-method","ifCatch":true},{"nodeName":"statement-169-_check() : int","category":"openclover-statement","ifCatch":true},{"nodeName":"statement-170-_check() : int","category":"openclover-statement","ifCatch":true},{"nodeName":"statement-171-_check() : int","category":"openclover-statement","ifCatch":true},{"nodeName":"statement-172-_check() : int","category":"openclover-statement","ifCatch":true},{"nodeName":"statement-173-_check() : int","category":"openclover-statement","ifCatch":true},{"nodeName":"statement-174-_check() : int","category":"openclover-statement","ifCatch":true},{"nodeName":"statement-175-_check() : int","category":"openclover-statement","ifCatch":true},{"nodeName":"branch-65-_check() : int","category":"openclover-branch","ifCatch":true},{"nodeName":"branch-66-_check() : int","category":"openclover-branch","ifCatch":false},{"nodeName":"statement-176-_check() : int","category":"openclover-statement","ifCatch":true},{"nodeName":"statement-177-_check() : int","category":"openclover-statement","ifCatch":true},{"nodeName":"statement-178-_check() : int","category":"openclover-statement","ifCatch":true},{"nodeName":"statement-179-_check() : int","category":"openclover-statement","ifCatch":true},{"nodeName":"branch-67-_check() : int","category":"openclover-branch","ifCatch":true},{"nodeName":"branch-68-_check() : int","category":"openclover-branch","ifCatch":true},{"nodeName":"statement-180-_check() : int","category":"openclover-statement","ifCatch":true},{"nodeName":"branch-69-_check() : int","category":"openclover-branch","ifCatch":true},{"nodeName":"branch-70-_check() : int","category":"openclover-branch","ifCatch":false},{"nodeName":"statement-181-_check() : int","category":"openclover-statement","ifCatch":true},{"nodeName":"method-49-doAddData(DATA,double) : void","category":"openclover-method","ifCatch":true},{"nodeName":"statement-182-doAddData(DATA,double) : void","category":"openclover-statement","ifCatch":true},{"nodeName":"method-50-doRemoveData(DATA,double) : void","category":"openclover-method","ifCatch":true},{"nodeName":"statement-183-doRemoveData(DATA,double) : void","category":"openclover-statement","ifCatch":true},{"nodeName":"method-51-checkMaxCapacity() : void","category":"openclover-method","ifCatch":true},{"nodeName":"statement-184-checkMaxCapacity() : void","category":"openclover-statement","ifCatch":true},{"nodeName":"branch-71-checkMaxCapacity() : void","category":"openclover-branch","ifCatch":true},{"nodeName":"branch-72-checkMaxCapacity() : void","category":"openclover-branch","ifCatch":true},{"nodeName":"statement-185-checkMaxCapacity() : void","category":"openclover-statement","ifCatch":true},{"nodeName":"statement-186-checkMaxCapacity() : void","category":"openclover-statement","ifCatch":true},{"nodeName":"statement-187-checkMaxCapacity() : void","category":"openclover-statement","ifCatch":true},{"nodeName":"statement-188-checkMaxCapacity() : void","category":"openclover-statement","ifCatch":true},{"nodeName":"statement-189-checkMaxCapacity() : void","category":"openclover-statement","ifCatch":true},{"nodeName":"branch-73-checkMaxCapacity() : void","category":"openclover-branch","ifCatch":true},{"nodeName":"branch-74-checkMaxCapacity() : void","category":"openclover-branch","ifCatch":true},{"nodeName":"statement-190-checkMaxCapacity() : void","category":"openclover-statement","ifCatch":true},{"nodeName":"statement-191-checkMaxCapacity() : void","category":"openclover-statement","ifCatch":true},{"nodeName":"statement-192-checkMaxCapacity() : void","category":"openclover-statement","ifCatch":true},{"nodeName":"statement-193-checkMaxCapacity() : void","category":"openclover-statement","ifCatch":true},{"nodeName":"statement-194-checkMaxCapacity() : void","category":"openclover-statement","ifCatch":true},{"nodeName":"statement-195-checkMaxCapacity() : void","category":"openclover-statement","ifCatch":true},{"nodeName":"statement-196-checkMaxCapacity() : void","category":"openclover-statement","ifCatch":true},{"nodeName":"statement-197-checkMaxCapacity() : void","category":"openclover-statement","ifCatch":true},{"nodeName":"statement-198-checkMaxCapacity() : void","category":"openclover-statement","ifCatch":true},{"nodeName":"branch-75-checkMaxCapacity() : void","category":"openclover-branch","ifCatch":true},{"nodeName":"branch-76-checkMaxCapacity() : void","category":"openclover-branch","ifCatch":true},{"nodeName":"statement-199-checkMaxCapacity() : void","category":"openclover-statement","ifCatch":true},{"nodeName":"statement-200-checkMaxCapacity() : void","category":"openclover-statement","ifCatch":true},{"nodeName":"branch-77-checkMaxCapacity() : void","category":"openclover-branch","ifCatch":true},{"nodeName":"branch-78-checkMaxCapacity() : void","category":"openclover-branch","ifCatch":false},{"nodeName":"statement-201-checkMaxCapacity() : void","category":"openclover-statement","ifCatch":true},{"nodeName":"method-52-newSplitNodeReplacement(DATA) : Node","category":"openclover-method","ifCatch":true},{"nodeName":"statement-202-newSplitNodeReplacement(DATA) : Node","category":"openclover-statement","ifCatch":true},{"nodeName":"method-53-addChild(IndexItem,double) : void","category":"openclover-method","ifCatch":true},{"nodeName":"statement-203-addChild(IndexItem,double) : void","category":"openclover-statement","ifCatch":true},{"nodeName":"method-54-removeData(DATA,double) : void","category":"openclover-method","ifCatch":true},{"nodeName":"statement-204-removeData(DATA,double) : void","category":"openclover-statement","ifCatch":true},{"nodeName":"statement-205-removeData(DATA,double) : void","category":"openclover-statement","ifCatch":true},{"nodeName":"branch-79-removeData(DATA,double) : void","category":"openclover-branch","ifCatch":true},{"nodeName":"branch-80-removeData(DATA,double) : void","category":"openclover-branch","ifCatch":true},{"nodeName":"statement-206-removeData(DATA,double) : void","category":"openclover-statement","ifCatch":true},{"nodeName":"method-55-getMinCapacity() : int","category":"openclover-method","ifCatch":true},{"nodeName":"statement-207-getMinCapacity() : int","category":"openclover-statement","ifCatch":true},{"nodeName":"method-56-updateMetrics(IndexItem,double) : void","category":"openclover-method","ifCatch":true},{"nodeName":"statement-208-updateMetrics(IndexItem,double) : void","category":"openclover-statement","ifCatch":true},{"nodeName":"statement-209-updateMetrics(IndexItem,double) : void","category":"openclover-statement","ifCatch":true},{"nodeName":"method-57-updateRadius(IndexItem) : void","category":"openclover-method","ifCatch":true},{"nodeName":"statement-210-updateRadius(IndexItem) : void","category":"openclover-statement","ifCatch":true},{"nodeName":"method-58-_checkMinCapacity() : void","category":"openclover-method","ifCatch":true},{"nodeName":"statement-211-_checkMinCapacity() : void","category":"openclover-statement","ifCatch":true},{"nodeName":"method-59-_checkMaxCapacity() : void","category":"openclover-method","ifCatch":true},{"nodeName":"branch-81-_checkMaxCapacity() : void","category":"openclover-branch","ifCatch":true},{"nodeName":"branch-82-_checkMaxCapacity() : void","category":"openclover-branch","ifCatch":false},{"nodeName":"method-60-_checkChildClass(IndexItem) : void","category":"openclover-method","ifCatch":true},{"nodeName":"statement-212-_checkChildClass(IndexItem) : void","category":"openclover-statement","ifCatch":true},{"nodeName":"method-61-_checkChildMetrics(IndexItem) : void","category":"openclover-method","ifCatch":true},{"nodeName":"statement-213-_checkChildMetrics(IndexItem) : void","category":"openclover-statement","ifCatch":true},{"nodeName":"branch-83-_checkChildMetrics(IndexItem) : void","category":"openclover-branch","ifCatch":true},{"nodeName":"branch-84-_checkChildMetrics(IndexItem) : void","category":"openclover-branch","ifCatch":false},{"nodeName":"statement-214-_checkChildMetrics(IndexItem) : void","category":"openclover-statement","ifCatch":true},{"nodeName":"branch-85-_checkChildMetrics(IndexItem) : void","category":"openclover-branch","ifCatch":true},{"nodeName":"branch-86-_checkChildMetrics(IndexItem) : void","category":"openclover-branch","ifCatch":false},{"nodeName":"method-62-_checkDistanceToParent() : void","category":"openclover-method","ifCatch":true},{"nodeName":"statement-215-_checkDistanceToParent() : void","category":"openclover-statement","ifCatch":true},{"nodeName":"method-63-mtree() : MTree<DATA>","category":"openclover-method","ifCatch":true},{"nodeName":"statement-216-mtree() : MTree<DATA>","category":"openclover-statement","ifCatch":true},{"nodeName":"method-64-getMinCapacity() : int","category":"openclover-method","ifCatch":false},{"nodeName":"statement-217-getMinCapacity() : int","category":"openclover-statement","ifCatch":false},{"nodeName":"method-65-_checkDistanceToParent() : void","category":"openclover-method","ifCatch":true},{"nodeName":"branch-87-_checkDistanceToParent() : void","category":"openclover-branch","ifCatch":true},{"nodeName":"branch-88-_checkDistanceToParent() : void","category":"openclover-branch","ifCatch":false},{"nodeName":"method-66-_checkMinCapacity() : void","category":"openclover-method","ifCatch":false},{"nodeName":"statement-218-_checkMinCapacity() : void","category":"openclover-statement","ifCatch":false},{"nodeName":"method-67-getMinCapacity() : int","category":"openclover-method","ifCatch":true},{"nodeName":"statement-219-getMinCapacity() : int","category":"openclover-statement","ifCatch":true},{"nodeName":"method-68-_checkMinCapacity() : void","category":"openclover-method","ifCatch":true},{"nodeName":"branch-89-_checkMinCapacity() : void","category":"openclover-branch","ifCatch":true},{"nodeName":"branch-90-_checkMinCapacity() : void","category":"openclover-branch","ifCatch":false},{"nodeName":"method-69-_checkDistanceToParent() : void","category":"openclover-method","ifCatch":true},{"nodeName":"branch-91-_checkDistanceToParent() : void","category":"openclover-branch","ifCatch":true},{"nodeName":"branch-92-_checkDistanceToParent() : void","category":"openclover-branch","ifCatch":false},{"nodeName":"method-70-doAddData(DATA,double) : void","category":"openclover-method","ifCatch":true},{"nodeName":"statement-220-doAddData(DATA,double) : void","category":"openclover-statement","ifCatch":true},{"nodeName":"branch-93-doAddData(DATA,double) : void","category":"openclover-branch","ifCatch":true},{"nodeName":"branch-94-doAddData(DATA,double) : void","category":"openclover-branch","ifCatch":false},{"nodeName":"statement-221-doAddData(DATA,double) : void","category":"openclover-statement","ifCatch":true},{"nodeName":"branch-95-doAddData(DATA,double) : void","category":"openclover-branch","ifCatch":true},{"nodeName":"branch-96-doAddData(DATA,double) : void","category":"openclover-branch","ifCatch":false},{"nodeName":"statement-222-doAddData(DATA,double) : void","category":"openclover-statement","ifCatch":true},{"nodeName":"method-71-addChild(IndexItem,double) : void","category":"openclover-method","ifCatch":true},{"nodeName":"branch-97-addChild(IndexItem,double) : void","category":"openclover-branch","ifCatch":true},{"nodeName":"branch-98-addChild(IndexItem,double) : void","category":"openclover-branch","ifCatch":false},{"nodeName":"statement-223-addChild(IndexItem,double) : void","category":"openclover-statement","ifCatch":true},{"nodeName":"branch-99-addChild(IndexItem,double) : void","category":"openclover-branch","ifCatch":true},{"nodeName":"branch-100-addChild(IndexItem,double) : void","category":"openclover-branch","ifCatch":false},{"nodeName":"statement-224-addChild(IndexItem,double) : void","category":"openclover-statement","ifCatch":true},{"nodeName":"method-72-newSplitNodeReplacement(DATA) : Node","category":"openclover-method","ifCatch":true},{"nodeName":"statement-225-newSplitNodeReplacement(DATA) : Node","category":"openclover-statement","ifCatch":true},{"nodeName":"method-73-doRemoveData(DATA,double) : void","category":"openclover-method","ifCatch":true},{"nodeName":"statement-226-doRemoveData(DATA,double) : void","category":"openclover-statement","ifCatch":true},{"nodeName":"branch-101-doRemoveData(DATA,double) : void","category":"openclover-branch","ifCatch":true},{"nodeName":"branch-102-doRemoveData(DATA,double) : void","category":"openclover-branch","ifCatch":true},{"nodeName":"statement-227-doRemoveData(DATA,double) : void","category":"openclover-statement","ifCatch":true},{"nodeName":"method-74-_checkChildClass(IndexItem) : void","category":"openclover-method","ifCatch":true},{"nodeName":"branch-103-_checkChildClass(IndexItem) : void","category":"openclover-branch","ifCatch":true},{"nodeName":"branch-104-_checkChildClass(IndexItem) : void","category":"openclover-branch","ifCatch":false},{"nodeName":"method-75-doAddData(DATA,double) : void","category":"openclover-method","ifCatch":true},{"nodeName":"method-76-CandidateChild(Node,double,double)","category":"openclover-method","ifCatch":true},{"nodeName":"statement-228-CandidateChild(Node,double,double)","category":"openclover-statement","ifCatch":true},{"nodeName":"statement-229-CandidateChild(Node,double,double)","category":"openclover-statement","ifCatch":true},{"nodeName":"statement-230-CandidateChild(Node,double,double)","category":"openclover-statement","ifCatch":true},{"nodeName":"statement-231-CandidateChild(Node,double,double)","category":"openclover-statement","ifCatch":true},{"nodeName":"statement-232-CandidateChild(Node,double,double)","category":"openclover-statement","ifCatch":true},{"nodeName":"statement-233-CandidateChild(Node,double,double)","category":"openclover-statement","ifCatch":true},{"nodeName":"statement-234-CandidateChild(Node,double,double)","category":"openclover-statement","ifCatch":true},{"nodeName":"statement-235-CandidateChild(Node,double,double)","category":"openclover-statement","ifCatch":true},{"nodeName":"statement-236-CandidateChild(Node,double,double)","category":"openclover-statement","ifCatch":true},{"nodeName":"branch-105-CandidateChild(Node,double,double)","category":"openclover-branch","ifCatch":true},{"nodeName":"branch-106-CandidateChild(Node,double,double)","category":"openclover-branch","ifCatch":true},{"nodeName":"statement-237-CandidateChild(Node,double,double)","category":"openclover-statement","ifCatch":true},{"nodeName":"statement-238-CandidateChild(Node,double,double)","category":"openclover-statement","ifCatch":true},{"nodeName":"branch-107-CandidateChild(Node,double,double)","category":"openclover-branch","ifCatch":true},{"nodeName":"branch-108-CandidateChild(Node,double,double)","category":"openclover-branch","ifCatch":true},{"nodeName":"statement-239-CandidateChild(Node,double,double)","category":"openclover-statement","ifCatch":true},{"nodeName":"statement-240-CandidateChild(Node,double,double)","category":"openclover-statement","ifCatch":true},{"nodeName":"branch-109-CandidateChild(Node,double,double)","category":"openclover-branch","ifCatch":true},{"nodeName":"branch-110-CandidateChild(Node,double,double)","category":"openclover-branch","ifCatch":true},{"nodeName":"statement-241-CandidateChild(Node,double,double)","category":"openclover-statement","ifCatch":true},{"nodeName":"statement-242-CandidateChild(Node,double,double)","category":"openclover-statement","ifCatch":true},{"nodeName":"branch-111-CandidateChild(Node,double,double)","category":"openclover-branch","ifCatch":true},{"nodeName":"branch-112-CandidateChild(Node,double,double)","category":"openclover-branch","ifCatch":true},{"nodeName":"statement-243-CandidateChild(Node,double,double)","category":"openclover-statement","ifCatch":true},{"nodeName":"statement-244-CandidateChild(Node,double,double)","category":"openclover-statement","ifCatch":true},{"nodeName":"statement-245-CandidateChild(Node,double,double)","category":"openclover-statement","ifCatch":true},{"nodeName":"statement-246-CandidateChild(Node,double,double)","category":"openclover-statement","ifCatch":true},{"nodeName":"statement-247-CandidateChild(Node,double,double)","category":"openclover-statement","ifCatch":true},{"nodeName":"branch-113-CandidateChild(Node,double,double)","category":"openclover-branch","ifCatch":true},{"nodeName":"branch-114-CandidateChild(Node,double,double)","category":"openclover-branch","ifCatch":false},{"nodeName":"statement-248-CandidateChild(Node,double,double)","category":"openclover-statement","ifCatch":true},{"nodeName":"branch-115-CandidateChild(Node,double,double)","category":"openclover-branch","ifCatch":true},{"nodeName":"branch-116-CandidateChild(Node,double,double)","category":"openclover-branch","ifCatch":true},{"nodeName":"statement-249-CandidateChild(Node,double,double)","category":"openclover-statement","ifCatch":true},{"nodeName":"statement-250-CandidateChild(Node,double,double)","category":"openclover-statement","ifCatch":true},{"nodeName":"statement-251-CandidateChild(Node,double,double)","category":"openclover-statement","ifCatch":true},{"nodeName":"method-77-addChild(IndexItem,double) : void","category":"openclover-method","ifCatch":true},{"nodeName":"statement-252-addChild(IndexItem,double) : void","category":"openclover-statement","ifCatch":true},{"nodeName":"method-78-ChildWithDistance(Node,double)","category":"openclover-method","ifCatch":true},{"nodeName":"statement-253-ChildWithDistance(Node,double)","category":"openclover-statement","ifCatch":true},{"nodeName":"statement-254-ChildWithDistance(Node,double)","category":"openclover-statement","ifCatch":true},{"nodeName":"statement-255-ChildWithDistance(Node,double)","category":"openclover-statement","ifCatch":true},{"nodeName":"statement-256-ChildWithDistance(Node,double)","category":"openclover-statement","ifCatch":true},{"nodeName":"statement-257-ChildWithDistance(Node,double)","category":"openclover-statement","ifCatch":true},{"nodeName":"branch-117-ChildWithDistance(Node,double)","category":"openclover-branch","ifCatch":true},{"nodeName":"branch-118-ChildWithDistance(Node,double)","category":"openclover-branch","ifCatch":true},{"nodeName":"statement-258-ChildWithDistance(Node,double)","category":"openclover-statement","ifCatch":true},{"nodeName":"statement-259-ChildWithDistance(Node,double)","category":"openclover-statement","ifCatch":true},{"nodeName":"statement-260-ChildWithDistance(Node,double)","category":"openclover-statement","ifCatch":true},{"nodeName":"statement-261-ChildWithDistance(Node,double)","category":"openclover-statement","ifCatch":true},{"nodeName":"branch-119-ChildWithDistance(Node,double)","category":"openclover-branch","ifCatch":false},{"nodeName":"branch-120-ChildWithDistance(Node,double)","category":"openclover-branch","ifCatch":true},{"nodeName":"statement-262-ChildWithDistance(Node,double)","category":"openclover-statement","ifCatch":false},{"nodeName":"branch-121-ChildWithDistance(Node,double)","category":"openclover-branch","ifCatch":false},{"nodeName":"branch-122-ChildWithDistance(Node,double)","category":"openclover-branch","ifCatch":false},{"nodeName":"statement-263-ChildWithDistance(Node,double)","category":"openclover-statement","ifCatch":false},{"nodeName":"statement-264-ChildWithDistance(Node,double)","category":"openclover-statement","ifCatch":false},{"nodeName":"statement-265-ChildWithDistance(Node,double)","category":"openclover-statement","ifCatch":false},{"nodeName":"statement-266-ChildWithDistance(Node,double)","category":"openclover-statement","ifCatch":false},{"nodeName":"statement-267-ChildWithDistance(Node,double)","category":"openclover-statement","ifCatch":false},{"nodeName":"statement-268-ChildWithDistance(Node,double)","category":"openclover-statement","ifCatch":false},{"nodeName":"branch-123-ChildWithDistance(Node,double)","category":"openclover-branch","ifCatch":false},{"nodeName":"branch-124-ChildWithDistance(Node,double)","category":"openclover-branch","ifCatch":false},{"nodeName":"statement-269-ChildWithDistance(Node,double)","category":"openclover-statement","ifCatch":false},{"nodeName":"branch-125-ChildWithDistance(Node,double)","category":"openclover-branch","ifCatch":false},{"nodeName":"branch-126-ChildWithDistance(Node,double)","category":"openclover-branch","ifCatch":false},{"nodeName":"statement-270-ChildWithDistance(Node,double)","category":"openclover-statement","ifCatch":false},{"nodeName":"statement-271-ChildWithDistance(Node,double)","category":"openclover-statement","ifCatch":false},{"nodeName":"statement-272-ChildWithDistance(Node,double)","category":"openclover-statement","ifCatch":false},{"nodeName":"statement-273-ChildWithDistance(Node,double)","category":"openclover-statement","ifCatch":true},{"nodeName":"statement-274-ChildWithDistance(Node,double)","category":"openclover-statement","ifCatch":true},{"nodeName":"method-79-newSplitNodeReplacement(DATA) : Node","category":"openclover-method","ifCatch":true},{"nodeName":"statement-275-newSplitNodeReplacement(DATA) : Node","category":"openclover-statement","ifCatch":true},{"nodeName":"method-80-doRemoveData(DATA,double) : void","category":"openclover-method","ifCatch":true},{"nodeName":"statement-276-doRemoveData(DATA,double) : void","category":"openclover-statement","ifCatch":true},{"nodeName":"statement-277-doRemoveData(DATA,double) : void","category":"openclover-statement","ifCatch":true},{"nodeName":"statement-278-doRemoveData(DATA,double) : void","category":"openclover-statement","ifCatch":true},{"nodeName":"branch-127-doRemoveData(DATA,double) : void","category":"openclover-branch","ifCatch":true},{"nodeName":"branch-128-doRemoveData(DATA,double) : void","category":"openclover-branch","ifCatch":true},{"nodeName":"statement-279-doRemoveData(DATA,double) : void","category":"openclover-statement","ifCatch":true},{"nodeName":"statement-280-doRemoveData(DATA,double) : void","category":"openclover-statement","ifCatch":true},{"nodeName":"branch-129-doRemoveData(DATA,double) : void","category":"openclover-branch","ifCatch":true},{"nodeName":"branch-130-doRemoveData(DATA,double) : void","category":"openclover-branch","ifCatch":true},{"nodeName":"statement-281-doRemoveData(DATA,double) : void","category":"openclover-statement","ifCatch":true},{"nodeName":"statement-282-doRemoveData(DATA,double) : void","category":"openclover-statement","ifCatch":true},{"nodeName":"statement-283-doRemoveData(DATA,double) : void","category":"openclover-statement","ifCatch":true},{"nodeName":"statement-284-doRemoveData(DATA,double) : void","category":"openclover-statement","ifCatch":true},{"nodeName":"statement-285-doRemoveData(DATA,double) : void","category":"openclover-statement","ifCatch":true},{"nodeName":"statement-286-doRemoveData(DATA,double) : void","category":"openclover-statement","ifCatch":true},{"nodeName":"statement-287-doRemoveData(DATA,double) : void","category":"openclover-statement","ifCatch":true},{"nodeName":"statement-288-doRemoveData(DATA,double) : void","category":"openclover-statement","ifCatch":false},{"nodeName":"statement-289-doRemoveData(DATA,double) : void","category":"openclover-statement","ifCatch":true},{"nodeName":"method-81-balanceChildren(Node) : Node","category":"openclover-method","ifCatch":true},{"nodeName":"statement-290-balanceChildren(Node) : Node","category":"openclover-statement","ifCatch":true},{"nodeName":"statement-291-balanceChildren(Node) : Node","category":"openclover-statement","ifCatch":true},{"nodeName":"statement-292-balanceChildren(Node) : Node","category":"openclover-statement","ifCatch":true},{"nodeName":"statement-293-balanceChildren(Node) : Node","category":"openclover-statement","ifCatch":true},{"nodeName":"statement-294-balanceChildren(Node) : Node","category":"openclover-statement","ifCatch":true},{"nodeName":"statement-295-balanceChildren(Node) : Node","category":"openclover-statement","ifCatch":true},{"nodeName":"statement-296-balanceChildren(Node) : Node","category":"openclover-statement","ifCatch":true},{"nodeName":"statement-297-balanceChildren(Node) : Node","category":"openclover-statement","ifCatch":true},{"nodeName":"branch-131-balanceChildren(Node) : Node","category":"openclover-branch","ifCatch":true},{"nodeName":"branch-132-balanceChildren(Node) : Node","category":"openclover-branch","ifCatch":true},{"nodeName":"statement-298-balanceChildren(Node) : Node","category":"openclover-statement","ifCatch":true},{"nodeName":"statement-299-balanceChildren(Node) : Node","category":"openclover-statement","ifCatch":true},{"nodeName":"branch-133-balanceChildren(Node) : Node","category":"openclover-branch","ifCatch":true},{"nodeName":"branch-134-balanceChildren(Node) : Node","category":"openclover-branch","ifCatch":true},{"nodeName":"statement-300-balanceChildren(Node) : Node","category":"openclover-statement","ifCatch":true},{"nodeName":"branch-135-balanceChildren(Node) : Node","category":"openclover-branch","ifCatch":true},{"nodeName":"branch-136-balanceChildren(Node) : Node","category":"openclover-branch","ifCatch":true},{"nodeName":"statement-301-balanceChildren(Node) : Node","category":"openclover-statement","ifCatch":true},{"nodeName":"statement-302-balanceChildren(Node) : Node","category":"openclover-statement","ifCatch":true},{"nodeName":"statement-303-balanceChildren(Node) : Node","category":"openclover-statement","ifCatch":true},{"nodeName":"branch-137-balanceChildren(Node) : Node","category":"openclover-branch","ifCatch":true},{"nodeName":"branch-138-balanceChildren(Node) : Node","category":"openclover-branch","ifCatch":true},{"nodeName":"statement-304-balanceChildren(Node) : Node","category":"openclover-statement","ifCatch":true},{"nodeName":"statement-305-balanceChildren(Node) : Node","category":"openclover-statement","ifCatch":true},{"nodeName":"statement-306-balanceChildren(Node) : Node","category":"openclover-statement","ifCatch":true},{"nodeName":"branch-139-balanceChildren(Node) : Node","category":"openclover-branch","ifCatch":true},{"nodeName":"branch-140-balanceChildren(Node) : Node","category":"openclover-branch","ifCatch":true},{"nodeName":"statement-307-balanceChildren(Node) : Node","category":"openclover-statement","ifCatch":true},{"nodeName":"statement-308-balanceChildren(Node) : Node","category":"openclover-statement","ifCatch":true},{"nodeName":"statement-309-balanceChildren(Node) : Node","category":"openclover-statement","ifCatch":true},{"nodeName":"statement-310-balanceChildren(Node) : Node","category":"openclover-statement","ifCatch":true},{"nodeName":"branch-141-balanceChildren(Node) : Node","category":"openclover-branch","ifCatch":true},{"nodeName":"branch-142-balanceChildren(Node) : Node","category":"openclover-branch","ifCatch":false},{"nodeName":"statement-311-balanceChildren(Node) : Node","category":"openclover-statement","ifCatch":true},{"nodeName":"statement-312-balanceChildren(Node) : Node","category":"openclover-statement","ifCatch":true},{"nodeName":"statement-313-balanceChildren(Node) : Node","category":"openclover-statement","ifCatch":true},{"nodeName":"statement-314-balanceChildren(Node) : Node","category":"openclover-statement","ifCatch":true},{"nodeName":"statement-315-balanceChildren(Node) : Node","category":"openclover-statement","ifCatch":true},{"nodeName":"statement-316-balanceChildren(Node) : Node","category":"openclover-statement","ifCatch":true},{"nodeName":"branch-143-balanceChildren(Node) : Node","category":"openclover-branch","ifCatch":true},{"nodeName":"branch-144-balanceChildren(Node) : Node","category":"openclover-branch","ifCatch":true},{"nodeName":"statement-317-balanceChildren(Node) : Node","category":"openclover-statement","ifCatch":true},{"nodeName":"statement-318-balanceChildren(Node) : Node","category":"openclover-statement","ifCatch":true},{"nodeName":"statement-319-balanceChildren(Node) : Node","category":"openclover-statement","ifCatch":true},{"nodeName":"branch-145-balanceChildren(Node) : Node","category":"openclover-branch","ifCatch":true},{"nodeName":"branch-146-balanceChildren(Node) : Node","category":"openclover-branch","ifCatch":false},{"nodeName":"statement-320-balanceChildren(Node) : Node","category":"openclover-statement","ifCatch":true},{"nodeName":"statement-321-balanceChildren(Node) : Node","category":"openclover-statement","ifCatch":true},{"nodeName":"method-82-_checkChildClass(IndexItem) : void","category":"openclover-method","ifCatch":true},{"nodeName":"branch-147-_checkChildClass(IndexItem) : void","category":"openclover-branch","ifCatch":true},{"nodeName":"branch-148-_checkChildClass(IndexItem) : void","category":"openclover-branch","ifCatch":false},{"nodeName":"method-83-RootLeafNode(DATA)","category":"openclover-method","ifCatch":true},{"nodeName":"statement-322-RootLeafNode(DATA)","category":"openclover-statement","ifCatch":true},{"nodeName":"method-84-removeData(DATA,double) : void","category":"openclover-method","ifCatch":true},{"nodeName":"statement-323-removeData(DATA,double) : void","category":"openclover-statement","ifCatch":true},{"nodeName":"statement-324-removeData(DATA,double) : void","category":"openclover-statement","ifCatch":true},{"nodeName":"branch-149-removeData(DATA,double) : void","category":"openclover-branch","ifCatch":true},{"nodeName":"branch-150-removeData(DATA,double) : void","category":"openclover-branch","ifCatch":false},{"nodeName":"statement-325-removeData(DATA,double) : void","category":"openclover-statement","ifCatch":true},{"nodeName":"method-85-getMinCapacity() : int","category":"openclover-method","ifCatch":true},{"nodeName":"statement-326-getMinCapacity() : int","category":"openclover-statement","ifCatch":true},{"nodeName":"method-86-_checkMinCapacity() : void","category":"openclover-method","ifCatch":true},{"nodeName":"branch-151-_checkMinCapacity() : void","category":"openclover-branch","ifCatch":true},{"nodeName":"branch-152-_checkMinCapacity() : void","category":"openclover-branch","ifCatch":false},{"nodeName":"method-87-RootNode(DATA)","category":"openclover-method","ifCatch":true},{"nodeName":"statement-327-RootNode(DATA)","category":"openclover-statement","ifCatch":true},{"nodeName":"method-88-removeData(DATA,double) : void","category":"openclover-method","ifCatch":true},{"nodeName":"statement-328-removeData(DATA,double) : void","category":"openclover-statement","ifCatch":true},{"nodeName":"statement-329-removeData(DATA,double) : void","category":"openclover-statement","ifCatch":true},{"nodeName":"statement-330-removeData(DATA,double) : void","category":"openclover-statement","ifCatch":true},{"nodeName":"statement-331-removeData(DATA,double) : void","category":"openclover-statement","ifCatch":true},{"nodeName":"statement-332-removeData(DATA,double) : void","category":"openclover-statement","ifCatch":true},{"nodeName":"branch-153-removeData(DATA,double) : void","category":"openclover-branch","ifCatch":true},{"nodeName":"branch-154-removeData(DATA,double) : void","category":"openclover-branch","ifCatch":true},{"nodeName":"statement-333-removeData(DATA,double) : void","category":"openclover-statement","ifCatch":true},{"nodeName":"branch-155-removeData(DATA,double) : void","category":"openclover-branch","ifCatch":true},{"nodeName":"branch-156-removeData(DATA,double) : void","category":"openclover-branch","ifCatch":false},{"nodeName":"statement-334-removeData(DATA,double) : void","category":"openclover-statement","ifCatch":true},{"nodeName":"statement-335-removeData(DATA,double) : void","category":"openclover-statement","ifCatch":true},{"nodeName":"statement-336-removeData(DATA,double) : void","category":"openclover-statement","ifCatch":true},{"nodeName":"statement-337-removeData(DATA,double) : void","category":"openclover-statement","ifCatch":true},{"nodeName":"statement-338-removeData(DATA,double) : void","category":"openclover-statement","ifCatch":true},{"nodeName":"statement-339-removeData(DATA,double) : void","category":"openclover-statement","ifCatch":true},{"nodeName":"method-89-getMinCapacity() : int","category":"openclover-method","ifCatch":true},{"nodeName":"statement-340-getMinCapacity() : int","category":"openclover-statement","ifCatch":true},{"nodeName":"method-90-_checkMinCapacity() : void","category":"openclover-method","ifCatch":true},{"nodeName":"branch-157-_checkMinCapacity() : void","category":"openclover-branch","ifCatch":true},{"nodeName":"branch-158-_checkMinCapacity() : void","category":"openclover-branch","ifCatch":false},{"nodeName":"method-91-InternalNode(DATA)","category":"openclover-method","ifCatch":true},{"nodeName":"statement-341-InternalNode(DATA)","category":"openclover-statement","ifCatch":true},{"nodeName":"method-92-LeafNode(DATA)","category":"openclover-method","ifCatch":true},{"nodeName":"statement-342-LeafNode(DATA)","category":"openclover-statement","ifCatch":true},{"nodeName":"method-93-Entry(DATA)","category":"openclover-method","ifCatch":true},{"nodeName":"statement-343-Entry(DATA)","category":"openclover-statement","ifCatch":true},{"nodeName":"method-94-Pair()","category":"openclover-method","ifCatch":true},{"nodeName":"method-95-Pair(T,T)","category":"openclover-method","ifCatch":true},{"nodeName":"statement-344-Pair(T,T)","category":"openclover-statement","ifCatch":true},{"nodeName":"statement-345-Pair(T,T)","category":"openclover-statement","ifCatch":true},{"nodeName":"method-96-get(int) : T","category":"openclover-method","ifCatch":true},{"nodeName":"statement-346-get(int) : T","category":"openclover-statement","ifCatch":true},{"nodeName":"statement-347-get(int) : T","category":"openclover-statement","ifCatch":true},{"nodeName":"statement-348-get(int) : T","category":"openclover-statement","ifCatch":true},{"nodeName":"statement-349-get(int) : T","category":"openclover-statement","ifCatch":true},{"nodeName":"statement-350-get(int) : T","category":"openclover-statement","ifCatch":true},{"nodeName":"statement-351-get(int) : T","category":"openclover-statement","ifCatch":true},{"nodeName":"statement-352-get(int) : T","category":"openclover-statement","ifCatch":true},{"nodeName":"method-97-PartitionFunctions()","category":"openclover-method","ifCatch":false},{"nodeName":"method-98-process(Pair<DATA>,Set<DATA>,DistanceFunction<? super DATA>) : Pair<Set<DATA>>","category":"openclover-method","ifCatch":true},{"nodeName":"statement-353-process(Pair<DATA>,Set<DATA>,DistanceFunction<? super DATA>) : Pair<Set<DATA>>","category":"openclover-statement","ifCatch":true},{"nodeName":"statement-354-process(Pair<DATA>,Set<DATA>,DistanceFunction<? super DATA>) : Pair<Set<DATA>>","category":"openclover-statement","ifCatch":true},{"nodeName":"method-99-compare(DATA,DATA) : int","category":"openclover-method","ifCatch":true},{"nodeName":"statement-355-compare(DATA,DATA) : int","category":"openclover-statement","ifCatch":true},{"nodeName":"statement-356-compare(DATA,DATA) : int","category":"openclover-statement","ifCatch":true},{"nodeName":"statement-357-compare(DATA,DATA) : int","category":"openclover-statement","ifCatch":true},{"nodeName":"statement-358-compare(DATA,DATA) : int","category":"openclover-statement","ifCatch":true},{"nodeName":"statement-359-compare(DATA,DATA) : int","category":"openclover-statement","ifCatch":true},{"nodeName":"method-100-compare(DATA,DATA) : int","category":"openclover-method","ifCatch":true},{"nodeName":"statement-360-compare(DATA,DATA) : int","category":"openclover-statement","ifCatch":true},{"nodeName":"statement-361-compare(DATA,DATA) : int","category":"openclover-statement","ifCatch":true},{"nodeName":"statement-362-compare(DATA,DATA) : int","category":"openclover-statement","ifCatch":true},{"nodeName":"statement-363-compare(DATA,DATA) : int","category":"openclover-statement","ifCatch":true},{"nodeName":"statement-364-compare(DATA,DATA) : int","category":"openclover-statement","ifCatch":true},{"nodeName":"statement-365-compare(DATA,DATA) : int","category":"openclover-statement","ifCatch":true},{"nodeName":"statement-366-compare(DATA,DATA) : int","category":"openclover-statement","ifCatch":true},{"nodeName":"branch-159-compare(DATA,DATA) : int","category":"openclover-branch","ifCatch":true},{"nodeName":"branch-160-compare(DATA,DATA) : int","category":"openclover-branch","ifCatch":true},{"nodeName":"statement-367-compare(DATA,DATA) : int","category":"openclover-statement","ifCatch":true},{"nodeName":"branch-161-compare(DATA,DATA) : int","category":"openclover-branch","ifCatch":true},{"nodeName":"branch-162-compare(DATA,DATA) : int","category":"openclover-branch","ifCatch":true},{"nodeName":"statement-368-compare(DATA,DATA) : int","category":"openclover-statement","ifCatch":true},{"nodeName":"statement-369-compare(DATA,DATA) : int","category":"openclover-statement","ifCatch":true},{"nodeName":"branch-163-compare(DATA,DATA) : int","category":"openclover-branch","ifCatch":true},{"nodeName":"branch-164-compare(DATA,DATA) : int","category":"openclover-branch","ifCatch":true},{"nodeName":"statement-370-compare(DATA,DATA) : int","category":"openclover-statement","ifCatch":true},{"nodeName":"statement-371-compare(DATA,DATA) : int","category":"openclover-statement","ifCatch":true},{"nodeName":"statement-372-compare(DATA,DATA) : int","category":"openclover-statement","ifCatch":true},{"nodeName":"branch-165-compare(DATA,DATA) : int","category":"openclover-branch","ifCatch":true},{"nodeName":"branch-166-compare(DATA,DATA) : int","category":"openclover-branch","ifCatch":true},{"nodeName":"statement-373-compare(DATA,DATA) : int","category":"openclover-statement","ifCatch":true},{"nodeName":"statement-374-compare(DATA,DATA) : int","category":"openclover-statement","ifCatch":true},{"nodeName":"branch-167-compare(DATA,DATA) : int","category":"openclover-branch","ifCatch":true},{"nodeName":"branch-168-compare(DATA,DATA) : int","category":"openclover-branch","ifCatch":true},{"nodeName":"statement-375-compare(DATA,DATA) : int","category":"openclover-statement","ifCatch":true},{"nodeName":"statement-376-compare(DATA,DATA) : int","category":"openclover-statement","ifCatch":true},{"nodeName":"statement-377-compare(DATA,DATA) : int","category":"openclover-statement","ifCatch":true},{"nodeName":"method-101-PromotionFunctions()","category":"openclover-method","ifCatch":false},{"nodeName":"method-102-process(Set<DATA>,DistanceFunction<? super DATA>) : Pair<DATA>","category":"openclover-method","ifCatch":true},{"nodeName":"statement-378-process(Set<DATA>,DistanceFunction<? super DATA>) : Pair<DATA>","category":"openclover-statement","ifCatch":true},{"nodeName":"statement-379-process(Set<DATA>,DistanceFunction<? super DATA>) : Pair<DATA>","category":"openclover-statement","ifCatch":true},{"nodeName":"method-103-SplitResult(Pair<DATA>,Pair<Set<DATA>>)","category":"openclover-method","ifCatch":true},{"nodeName":"statement-380-SplitResult(Pair<DATA>,Pair<Set<DATA>>)","category":"openclover-statement","ifCatch":true},{"nodeName":"statement-381-SplitResult(Pair<DATA>,Pair<Set<DATA>>)","category":"openclover-statement","ifCatch":true},{"nodeName":"method-104-Utils()","category":"openclover-method","ifCatch":false},{"nodeName":"method-105-minMax(Iterable<T>) : Pair<T>","category":"openclover-method","ifCatch":true},{"nodeName":"statement-382-minMax(Iterable<T>) : Pair<T>","category":"openclover-statement","ifCatch":true},{"nodeName":"statement-383-minMax(Iterable<T>) : Pair<T>","category":"openclover-statement","ifCatch":true},{"nodeName":"branch-169-minMax(Iterable<T>) : Pair<T>","category":"openclover-branch","ifCatch":true},{"nodeName":"branch-170-minMax(Iterable<T>) : Pair<T>","category":"openclover-branch","ifCatch":true},{"nodeName":"statement-384-minMax(Iterable<T>) : Pair<T>","category":"openclover-statement","ifCatch":true},{"nodeName":"statement-385-minMax(Iterable<T>) : Pair<T>","category":"openclover-statement","ifCatch":true},{"nodeName":"statement-386-minMax(Iterable<T>) : Pair<T>","category":"openclover-statement","ifCatch":true},{"nodeName":"statement-387-minMax(Iterable<T>) : Pair<T>","category":"openclover-statement","ifCatch":true},{"nodeName":"branch-171-minMax(Iterable<T>) : Pair<T>","category":"openclover-branch","ifCatch":true},{"nodeName":"branch-172-minMax(Iterable<T>) : Pair<T>","category":"openclover-branch","ifCatch":true},{"nodeName":"statement-388-minMax(Iterable<T>) : Pair<T>","category":"openclover-statement","ifCatch":true},{"nodeName":"statement-389-minMax(Iterable<T>) : Pair<T>","category":"openclover-statement","ifCatch":true},{"nodeName":"branch-173-minMax(Iterable<T>) : Pair<T>","category":"openclover-branch","ifCatch":true},{"nodeName":"branch-174-minMax(Iterable<T>) : Pair<T>","category":"openclover-branch","ifCatch":true},{"nodeName":"statement-390-minMax(Iterable<T>) : Pair<T>","category":"openclover-statement","ifCatch":true},{"nodeName":"statement-391-minMax(Iterable<T>) : Pair<T>","category":"openclover-statement","ifCatch":true},{"nodeName":"branch-175-minMax(Iterable<T>) : Pair<T>","category":"openclover-branch","ifCatch":true},{"nodeName":"branch-176-minMax(Iterable<T>) : Pair<T>","category":"openclover-branch","ifCatch":true},{"nodeName":"statement-392-minMax(Iterable<T>) : Pair<T>","category":"openclover-statement","ifCatch":true},{"nodeName":"statement-393-minMax(Iterable<T>) : Pair<T>","category":"openclover-statement","ifCatch":true},{"nodeName":"method-106-randomSample(Collection<T>,int) : List<T>","category":"openclover-method","ifCatch":true},{"nodeName":"statement-394-randomSample(Collection<T>,int) : List<T>","category":"openclover-statement","ifCatch":true},{"nodeName":"statement-395-randomSample(Collection<T>,int) : List<T>","category":"openclover-statement","ifCatch":true},{"nodeName":"statement-396-randomSample(Collection<T>,int) : List<T>","category":"openclover-statement","ifCatch":true},{"nodeName":"statement-397-randomSample(Collection<T>,int) : List<T>","category":"openclover-statement","ifCatch":true},{"nodeName":"branch-177-randomSample(Collection<T>,int) : List<T>","category":"openclover-branch","ifCatch":true},{"nodeName":"branch-178-randomSample(Collection<T>,int) : List<T>","category":"openclover-branch","ifCatch":true},{"nodeName":"statement-398-randomSample(Collection<T>,int) : List<T>","category":"openclover-statement","ifCatch":true},{"nodeName":"statement-399-randomSample(Collection<T>,int) : List<T>","category":"openclover-statement","ifCatch":true},{"nodeName":"statement-400-randomSample(Collection<T>,int) : List<T>","category":"openclover-statement","ifCatch":true},{"nodeName":"statement-401-randomSample(Collection<T>,int) : List<T>","category":"openclover-statement","ifCatch":true},{"nodeName":"statement-402-randomSample(Collection<T>,int) : List<T>","category":"openclover-statement","ifCatch":true},{"nodeName":"branch-179-randomSample(Collection<T>,int) : List<T>","category":"openclover-branch","ifCatch":true},{"nodeName":"branch-180-randomSample(Collection<T>,int) : List<T>","category":"openclover-branch","ifCatch":true},{"nodeName":"statement-403-randomSample(Collection<T>,int) : List<T>","category":"openclover-statement","ifCatch":true},{"nodeName":"statement-404-randomSample(Collection<T>,int) : List<T>","category":"openclover-statement","ifCatch":true},{"nodeName":"statement-405-randomSample(Collection<T>,int) : List<T>","category":"openclover-statement","ifCatch":true}]